fractal_noise/__init__.py
fractal_noise-2.0.4.dist-info/LICENSE
fractal_noise-2.0.4.dist-info/METADATA
fractal_noise-2.0.4.dist-info/WHEEL
fractal_noise-2.0.4.dist-info/top_level.txt
fractal_noise-2.0.4.dist-info/RECORD
