Metadata-Version: 2.1
Name: fractal-noise
Version: 2.0.4
Summary: Python implementation for Fractal Noise, ideal for creating realistic terrain, cloud-like textures, and intricate visual effects.
Home-page: UNKNOWN
Author: Sophia Shovkovy
Author-email: sophiashovkovy@gmail.com
License: UNKNOWN
Platform: UNKNOWN
License-File: LICENSE
Requires-Dist: numpy
Requires-Dist: perlin-noise
